odoo9_addon_account_payment_order_return-9.0.1.0.0-py2.7-nspkg.pth
odoo9_addon_account_payment_order_return-9.0.1.0.0.dist-info/DESCRIPTION.rst
odoo9_addon_account_payment_order_return-9.0.1.0.0.dist-info/METADATA
odoo9_addon_account_payment_order_return-9.0.1.0.0.dist-info/RECORD
odoo9_addon_account_payment_order_return-9.0.1.0.0.dist-info/WHEEL
odoo9_addon_account_payment_order_return-9.0.1.0.0.dist-info/metadata.json
odoo9_addon_account_payment_order_return-9.0.1.0.0.dist-info/namespace_packages.txt
odoo9_addon_account_payment_order_return-9.0.1.0.0.dist-info/top_level.txt
odoo_addons/account_payment_order_return/README.rst
odoo_addons/account_payment_order_return/__init__.py
odoo_addons/account_payment_order_return/__openerp__.py
odoo_addons/account_payment_order_return/i18n/es.po
odoo_addons/account_payment_order_return/static/description/icon.png
odoo_addons/account_payment_order_return/tests/__init__.py
odoo_addons/account_payment_order_return/tests/test_account_payment_order_return.py
odoo_addons/account_payment_order_return/wizard/__init__.py
odoo_addons/account_payment_order_return/wizard/account_payment_line_create.py
odoo_addons/account_payment_order_return/wizard/account_payment_line_create_view.xml
